threads_api/__init__.py
threads_api/src/__init__.py
threads_api/src/anotherlogger.py
threads_api/src/settings.py
threads_api/src/threads_api.py
threads_api/src/types.py
threads_api/src/http_sessions/__init__.py
threads_api/src/http_sessions/abstract_session.py
threads_api/src/http_sessions/aiohttp_session.py
threads_api/src/http_sessions/instagrapi_session.py
threads_api/src/http_sessions/requests_session.py
threads_api/tests/__init__.py
threads_api/tests/ut/__init__.py
threads_api/tests/ut/get_post_test.py
threads_api-1.2.0.dist-info/LICENSE
threads_api-1.2.0.dist-info/METADATA
threads_api-1.2.0.dist-info/WHEEL
threads_api-1.2.0.dist-info/top_level.txt
threads_api-1.2.0.dist-info/RECORD
