Metadata-Version: 2.1
Name: threads-api
Version: 1.2.0
Summary: Unofficial Python client for Meta Threads.net API
Home-page: https://github.com/danie1/threads-api
Author: Daniel Saad
Author-email: danielsaad777@gmail.com
License: UNKNOWN
Platform: UNKNOWN
Classifier: Operating System :: OS Independent
Classifier: Intended Audience :: Developers
Classifier: License :: OSI Approved :: MIT License
Classifier: Programming Language :: Python :: 3.9
Classifier: Programming Language :: Python :: 3.10
Classifier: Programming Language :: Python :: 3.11
License-File: LICENSE
